artetv_dl/__init__.py
artetv_dl/__main__.py
artetv_dl-1.1.0.dist-info/AUTHORS
artetv_dl-1.1.0.dist-info/LICENSE
artetv_dl-1.1.0.dist-info/METADATA
artetv_dl-1.1.0.dist-info/WHEEL
artetv_dl-1.1.0.dist-info/entry_points.txt
artetv_dl-1.1.0.dist-info/pbr.json
artetv_dl-1.1.0.dist-info/top_level.txt
artetv_dl-1.1.0.dist-info/RECORD
